doltpy/__init__.py
doltpy/cli/__init__.py
doltpy/cli/dolt.py
doltpy/cli/read.py
doltpy/cli/write.py
doltpy/etl/__init__.py
doltpy/etl/loaders.py
doltpy/etl/wrappers.py
doltpy/shared/__init__.py
doltpy/shared/helpers.py
doltpy/shared/system_helpers.py
doltpy/sql/__init__.py
doltpy/sql/helpers.py
doltpy/sql/sql.py
doltpy/sql/sync/README.md
doltpy/sql/sync/__init__.py
doltpy/sql/sync/db_tools.py
doltpy/sql/sync/dolt.py
doltpy/sql/sync/mysql.py
doltpy/sql/sync/oracle.py
doltpy/sql/sync/postgres.py
doltpy/sql/sync/sql_sync_diagram.png
doltpy/sql/sync/sync_tools.py
doltpy/types/__init__.py
doltpy/types/dolt.py
doltpy-2.0.14.dist-info/METADATA
doltpy-2.0.14.dist-info/entry_points.txt
doltpy-2.0.14.dist-info/WHEEL
doltpy-2.0.14.dist-info/LICENSE.txt
doltpy-2.0.14.dist-info/RECORD
