Metadata-Version: 2.1
Name: doltpy
Version: 2.0.14
Summary: A Python package for using Dolt database via Python.
Home-page: https://github.com/dolthub/doltpy
Keywords: Dolt,Liquidata,DoltHub,ETL,ELT,MLOps
Author: Oscar Batori
Author-email: oscar@dolthub.com
Requires-Python: >=3.6.1,<4.0
Classifier: Programming Language :: Python :: 3
Classifier: Programming Language :: Python :: 3.7
Classifier: Programming Language :: Python :: 3.8
Classifier: Programming Language :: Python :: 3.9
Classifier: Programming Language :: Python :: 3.10
Classifier: Programming Language :: Python :: 3.11
Provides-Extra: oracle
Provides-Extra: pg
Requires-Dist: SQLAlchemy (==1.3.18)
Requires-Dist: attrs (==19.3.0)
Requires-Dist: decorator (==4.4.2)
Requires-Dist: doltcli (>=0.1.14,<0.2.0)
Requires-Dist: more-itertools (>=8.6.0,<9.0.0)
Requires-Dist: mysql-connector-python (>=8.0.20,<9.0.0)
Requires-Dist: numpy (>=1.19.0)
Requires-Dist: packaging (==20.4)
Requires-Dist: pandas (>=1.0.5)
Requires-Dist: pluggy (==0.13.1)
Requires-Dist: protobuf (==3.12.2)
Requires-Dist: psutil (==5.7.2)
Requires-Dist: pyarrow (>=6.0.0)
Requires-Dist: pyparsing (==2.4.7)
Requires-Dist: python-dateutil (==2.8.1)
Requires-Dist: pytz (==2021.3)
Requires-Dist: retry (==0.9.2)
Requires-Dist: six (==1.15.0)
Requires-Dist: wcwidth (==0.2.5)
